odoo/addons/ssi_hr_employee/README.rst
odoo/addons/ssi_hr_employee/__init__.py
odoo/addons/ssi_hr_employee/__manifest__.py
odoo/addons/ssi_hr_employee/menu.xml
odoo/addons/ssi_hr_employee/demo/employee_competency.xml
odoo/addons/ssi_hr_employee/demo/employee_skill.xml
odoo/addons/ssi_hr_employee/demo/hr_employment_status_demo.xml
odoo/addons/ssi_hr_employee/demo/hr_job_grade_category_demo.xml
odoo/addons/ssi_hr_employee/demo/hr_job_grade_demo.xml
odoo/addons/ssi_hr_employee/models/__init__.py
odoo/addons/ssi_hr_employee/models/employee_competency.py
odoo/addons/ssi_hr_employee/models/employee_skill.py
odoo/addons/ssi_hr_employee/models/hr_employee.py
odoo/addons/ssi_hr_employee/models/hr_employment_status.py
odoo/addons/ssi_hr_employee/models/hr_job.py
odoo/addons/ssi_hr_employee/models/hr_job_family.py
odoo/addons/ssi_hr_employee/models/hr_job_family_grade.py
odoo/addons/ssi_hr_employee/models/hr_job_family_level.py
odoo/addons/ssi_hr_employee/models/hr_job_grade.py
odoo/addons/ssi_hr_employee/models/hr_job_grade_category.py
odoo/addons/ssi_hr_employee/models/job_description.py
odoo/addons/ssi_hr_employee/security/ir.model.access.csv
odoo/addons/ssi_hr_employee/security/res_group_data.xml
odoo/addons/ssi_hr_employee/static/description/icon.png
odoo/addons/ssi_hr_employee/views/employee_competency_views.xml
odoo/addons/ssi_hr_employee/views/employee_skill_views.xml
odoo/addons/ssi_hr_employee/views/hr_employee_views.xml
odoo/addons/ssi_hr_employee/views/hr_employment_status_views.xml
odoo/addons/ssi_hr_employee/views/hr_job_family_grade_views.xml
odoo/addons/ssi_hr_employee/views/hr_job_family_level_views.xml
odoo/addons/ssi_hr_employee/views/hr_job_family_views.xml
odoo/addons/ssi_hr_employee/views/hr_job_grade_category_views.xml
odoo/addons/ssi_hr_employee/views/hr_job_grade_views.xml
odoo/addons/ssi_hr_employee/views/hr_job_views.xml
odoo/addons/ssi_hr_employee/views/job_description_views.xml
odoo14_addon_ssi_hr_employee-14.0.2.10.0.dist-info/METADATA
odoo14_addon_ssi_hr_employee-14.0.2.10.0.dist-info/WHEEL
odoo14_addon_ssi_hr_employee-14.0.2.10.0.dist-info/top_level.txt
odoo14_addon_ssi_hr_employee-14.0.2.10.0.dist-info/RECORD
