Metadata-Version: 2.1
Name: odoo14-addon-ssi_hr_employee
Version: 14.0.2.10.0
Summary: HR Employee
Home-page: https://simetri-sinergi.id
Author: PT. Simetri Sinergi Indonesia, OpenSynergy Indonesia
License: AGPL-3
Classifier: Programming Language :: Python
Classifier: Framework :: Odoo
Classifier: Framework :: Odoo :: 14.0
Classifier: License :: OSI Approved :: GNU Affero General Public License v3
Requires-Python: >=3.6
Requires-Dist: odoo14-addon-ssi-hr-employee-experience-from-work-address
Requires-Dist: odoo14-addon-ssi-hr-employee-language-from-work-address
Requires-Dist: odoo14-addon-ssi-hr-employee-personal-from-work-address
Requires-Dist: odoo14-addon-ssi-master-data-mixin
Requires-Dist: odoo<14.1dev,>=14.0a
